{"song":{"sectionLengths":[],"player1":"bf","notes":[{"sectionNotes":[],"lengthInSteps":16,"typeOfSection":0,"mustHitSection":true},{"sectionNotes":[],"lengthInSteps":16,"typeOfSection":0,"mustHitSection":true},{"sectionNotes":[],"lengthInSteps":16,"typeOfSection":0,"mustHitSection":true},{"sectionNotes":[],"lengthInSteps":16,"typeOfSection":0,"mustHitSection":true},{"sectionNotes":[],"lengthInSteps":16,"typeOfSection":0,"mustHitSection":true},{"sectionNotes":[],"lengthInSteps":16,"typeOfSection":0,"mustHitSection":true},{"sectionNotes":[],"lengthInSteps":16,"typeOfSection":0,"mustHitSection":true},{"sectionNotes":[],"lengthInSteps":16,"typeOfSection":0,"mustHitSection":true},{"sectionNotes":[],"lengthInSteps":16,"typeOfSection":0,"mustHitSection":true},{"sectionNotes":[],"lengthInSteps":16,"typeOfSection":0,"mustHitSection":true},{"sectionNotes":[],"lengthInSteps":16,"typeOfSection":0,"mustHitSection":true},{"sectionNotes":[],"lengthInSteps":16,"typeOfSection":0,"mustHitSection":true},{"sectionNotes":[],"lengthInSteps":16,"typeOfSection":0,"mustHitSection":true},{"sectionNotes":[],"lengthInSteps":16,"typeOfSection":0,"mustHitSection":true},{"sectionNotes":[],"lengthInSteps":16,"typeOfSection":0,"mustHitSection":true},{"sectionNotes":[],"lengthInSteps":16,"typeOfSection":0,"mustHitSection":true},{"sectionNotes":[],"lengthInSteps":16,"typeOfSection":0,"mustHitSection":true},{"sectionNotes":[],"lengthInSteps":16,"typeOfSection":0,"mustHitSection":true},{"sectionNotes":[],"lengthInSteps":16,"typeOfSection":0,"mustHitSection":true},{"sectionNotes":[[22800,1,1114.28571428571]],"lengthInSteps":16,"typeOfSection":0,"mustHitSection":false},{"sectionNotes":[[24000,1,514.285714285714],[24600,1,514.285714285714]],"lengthInSteps":16,"typeOfSection":0,"mustHitSection":false},{"sectionNotes":[[25200,0,1114.28571428571]],"lengthInSteps":16,"typeOfSection":0,"mustHitSection":false},{"sectionNotes":[[26400,0,514.285714285714],[27000,0,514.285714285714]],"lengthInSteps":16,"typeOfSection":0,"mustHitSection":false},{"sectionNotes":[[27600,2,1114.28571428571]],"lengthInSteps":16,"typeOfSection":0,"mustHitSection":true},{"sectionNotes":[[28800,3,514.285714285714],[29400,3,514.285714285714]],"lengthInSteps":16,"typeOfSection":0,"mustHitSection":true},{"sectionNotes":[[31050,1,0],[30000,1,225],[30300,1,225],[30750,1,150]],"lengthInSteps":16,"typeOfSection":0,"mustHitSection":true},{"sectionNotes":[[31350,1,0],[31650,1,0],[31800,1,75],[32100,1,150]],"lengthInSteps":16,"typeOfSection":0,"mustHitSection":true},{"sectionNotes":[[32400,1,525],[33000,1,225],[33300,1,225]],"lengthInSteps":16,"typeOfSection":0,"mustHitSection":false},{"sectionNotes":[[33600,1,225],[33900,1,225],[34200,1,0],[34350,1,0],[34500,1,0],[34650,1,0]],"lengthInSteps":16,"typeOfSection":0,"mustHitSection":false},{"sectionNotes":[[34800,0,225],[35100,0,0],[35250,0,0],[35400,0,0],[35550,0,0],[35700,0,225]],"lengthInSteps":16,"typeOfSection":0,"mustHitSection":false},{"sectionNotes":[[36000,0,225],[36300,0,0],[36450,0,0],[36600,0,225],[36900,0,0]],"lengthInSteps":16,"typeOfSection":0,"mustHitSection":false},{"sectionNotes":[[37200,1,225],[37500,1,225],[37800,1,225],[38100,1,225]],"lengthInSteps":16,"typeOfSection":0,"mustHitSection":true},{"typeOfSection":0,"sectionNotes":[[38400,3,225],[38700,0,0],[38850,3,225],[39150,0,0],[39300,3,225]],"lengthInSteps":16,"bpm":100,"changeBPM":false,"mustHitSection":true},{"typeOfSection":0,"sectionNotes":[[39600,1,225],[39900,1,225],[40200,1,225],[40500,1,225]],"lengthInSteps":16,"altAnim":false,"bpm":100,"changeBPM":false,"mustHitSection":true},{"lengthInSteps":16,"typeOfSection":0,"sectionNotes":[[40800,0,0],[40950,1,225],[41250,0,0],[41400,1,225],[41700,0,0],[41850,0,0]],"altAnim":false,"bpm":100,"changeBPM":false,"mustHitSection":true},{"sectionNotes":[[42000,1,525],[42600,1,0],[42750,1,0],[42900,3,225]],"typeOfSection":0,"lengthInSteps":16,"altAnim":false,"mustHitSection":false,"changeBPM":false,"bpm":175},{"sectionNotes":[[43200,2,225],[43650,2,225],[43500,3,0],[43950,3,0],[44100,3,0],[44250,3,0]],"typeOfSection":0,"lengthInSteps":16,"altAnim":false,"mustHitSection":false,"changeBPM":false,"bpm":175},{"sectionNotes":[[44400,3,375],[45000,3,375]],"typeOfSection":0,"lengthInSteps":16,"altAnim":false,"mustHitSection":false,"changeBPM":false,"bpm":175},{"sectionNotes":[[45600,3,375],[46200,0,0],[46350,0,0],[46500,0,150]],"typeOfSection":0,"lengthInSteps":16,"altAnim":false,"mustHitSection":false,"changeBPM":false,"bpm":175},{"sectionNotes":[[46800,0,450],[47400,1,450]],"typeOfSection":0,"lengthInSteps":16,"altAnim":false,"mustHitSection":true,"changeBPM":false,"bpm":175},{"sectionNotes":[[48000,2,225],[48300,3,0],[48450,2,225],[48750,3,0],[48900,2,225]],"typeOfSection":0,"lengthInSteps":16,"altAnim":false,"mustHitSection":true,"changeBPM":false,"bpm":175},{"sectionNotes":[[49200,0,0],[49350,2,0],[49500,1,0],[49650,2,0],[49800,0,0],[49950,2,0],[50100,1,0],[50250,2,0]],"typeOfSection":0,"lengthInSteps":16,"altAnim":false,"mustHitSection":true,"changeBPM":false,"bpm":175},{"sectionNotes":[[50400,1,225],[50700,2,0],[50850,1,225],[51150,1,225],[51450,2,0]],"typeOfSection":0,"lengthInSteps":16,"altAnim":false,"mustHitSection":true,"changeBPM":false,"bpm":175},{"sectionNotes":[[51600,1,0],[51750,0,225],[52050,1,0],[52200,1,0],[52350,0,225]],"typeOfSection":0,"lengthInSteps":16,"altAnim":false,"mustHitSection":false,"changeBPM":false,"bpm":175},{"sectionNotes":[[52800,1,0],[53025,1,0],[53250,1,0],[53475,1,0],[53700,1,0]],"typeOfSection":0,"lengthInSteps":16,"altAnim":false,"mustHitSection":false,"changeBPM":false,"bpm":175},{"sectionNotes":[[54000,0,0],[54450,0,0],[54600,0,0],[54750,3,0],[54900,0,0],[55050,0,0],[55125,1,0],[54150,3,37.5]],"typeOfSection":0,"lengthInSteps":16,"altAnim":false,"mustHitSection":true,"changeBPM":false,"bpm":175},{"sectionNotes":[[55200,0,0],[55350,3,0],[55500,0,0],[55650,3,0],[55800,0,0],[55950,3,0],[56100,0,0]],"typeOfSection":0,"lengthInSteps":16,"altAnim":false,"mustHitSection":true,"changeBPM":false,"bpm":175},{"sectionNotes":[[56400,1,375],[57150,1,375]],"typeOfSection":0,"lengthInSteps":16,"altAnim":false,"mustHitSection":false,"changeBPM":false,"bpm":175},{"sectionNotes":[[57600,2,0],[57900,2,0],[58050,0,0],[57750,0,0],[58425,1,300],[58200,2,150]],"typeOfSection":0,"lengthInSteps":16,"altAnim":false,"mustHitSection":false,"changeBPM":false,"bpm":175},{"sectionNotes":[[58800,1,225],[59700,1,225]],"typeOfSection":0,"lengthInSteps":16,"altAnim":false,"mustHitSection":true,"changeBPM":false,"bpm":175},{"sectionNotes":[],"typeOfSection":0,"lengthInSteps":16,"altAnim":false,"mustHitSection":true,"changeBPM":false,"bpm":175},{"sectionNotes":[[61200,0,375],[61650,1,0],[61800,0,225],[62100,0,225]],"typeOfSection":0,"lengthInSteps":16,"altAnim":false,"mustHitSection":false,"changeBPM":false,"bpm":175},{"sectionNotes":[[62400,1,0],[62550,3,0],[62850,0,375],[63300,0,0],[63450,0,0],[62700,0,0]],"typeOfSection":0,"lengthInSteps":16,"altAnim":false,"mustHitSection":false,"changeBPM":false,"bpm":175},{"sectionNotes":[[63600,2,225],[63900,2,0],[64050,2,0],[64200,2,0],[64350,2,0],[64500,2,0],[64650,2,0]],"typeOfSection":0,"lengthInSteps":16,"altAnim":false,"mustHitSection":false,"changeBPM":false,"bpm":175},{"sectionNotes":[[64800,0,525],[65400,0,525]],"typeOfSection":0,"lengthInSteps":16,"altAnim":false,"mustHitSection":false,"changeBPM":false,"bpm":175},{"sectionNotes":[[66000,1,225],[66300,0,0],[66450,0,0],[66600,1,225],[66900,3,0],[67050,3,0]],"typeOfSection":0,"lengthInSteps":16,"altAnim":false,"mustHitSection":true,"changeBPM":false,"bpm":175},{"sectionNotes":[[67200,0,0],[67350,0,0],[67800,2,0],[67950,2,0],[68100,2,0],[68250,2,0],[68325,2,0],[67500,1,225]],"typeOfSection":0,"lengthInSteps":16,"altAnim":false,"mustHitSection":true,"changeBPM":false,"bpm":175},{"sectionNotes":[[68550,0,0],[68625,1,0],[69000,0,0],[69075,1,0],[69225,0,0],[69300,2,0],[69450,1,0],[68775,0,0],[68850,1,0],[68400,1,0]],"typeOfSection":0,"lengthInSteps":16,"altAnim":false,"mustHitSection":true,"changeBPM":false,"bpm":175},{"sectionNotes":[[69750,1,0],[69900,0,0],[70500,0,225],[70200,0,225],[69600,0,0],[70050,2,0]],"typeOfSection":0,"lengthInSteps":16,"altAnim":false,"mustHitSection":true,"changeBPM":false,"bpm":175},{"sectionNotes":[[70800,3,225],[71100,3,225],[71400,0,225],[71700,0,0],[71850,0,0]],"typeOfSection":0,"lengthInSteps":16,"altAnim":false,"mustHitSection":false,"changeBPM":false,"bpm":175},{"sectionNotes":[[72000,1,225],[72300,3,225],[72600,1,225],[72900,0,0],[73050,0,0]],"typeOfSection":0,"lengthInSteps":16,"altAnim":false,"mustHitSection":false,"changeBPM":false,"bpm":175},{"sectionNotes":[[73200,3,0],[73350,3,0],[73650,3,0],[73800,3,0],[73950,3,0],[74100,3,0]],"typeOfSection":0,"lengthInSteps":16,"altAnim":false,"mustHitSection":false,"changeBPM":false,"bpm":175},{"sectionNotes":[[74400,2,225],[74700,0,0],[75000,0,0],[75150,0,0],[75450,0,0]],"typeOfSection":0,"lengthInSteps":16,"altAnim":false,"mustHitSection":false,"changeBPM":false,"bpm":175},{"sectionNotes":[[75600,1,525],[76200,3,525]],"typeOfSection":0,"lengthInSteps":16,"altAnim":false,"mustHitSection":true,"changeBPM":false,"bpm":175},{"sectionNotes":[[76800,0,225],[77100,3,225],[77400,0,225],[77700,2,225]],"typeOfSection":0,"lengthInSteps":16,"altAnim":false,"mustHitSection":true,"changeBPM":false,"bpm":175},{"sectionNotes":[[78000,1,225],[78600,1,225],[78975,1,0],[79125,1,0],[78375,1,0],[78525,1,0]],"typeOfSection":0,"lengthInSteps":16,"altAnim":false,"mustHitSection":true,"changeBPM":false,"bpm":175},{"sectionNotes":[[79200,2,0],[79350,0,0],[79500,3,0],[79650,2,0],[79800,0,0],[79950,3,0],[80100,0,0],[80250,2,0]],"typeOfSection":0,"lengthInSteps":16,"altAnim":false,"mustHitSection":true,"changeBPM":false,"bpm":175},{"sectionNotes":[[80400,0,1575]],"typeOfSection":0,"lengthInSteps":16,"altAnim":false,"mustHitSection":false,"changeBPM":false,"bpm":175},{"sectionNotes":[],"typeOfSection":0,"lengthInSteps":16,"altAnim":false,"mustHitSection":false,"changeBPM":false,"bpm":175},{"sectionNotes":[[82800,0,0],[82950,0,0],[83400,0,0],[83550,0,0],[83850,0,0]],"typeOfSection":0,"lengthInSteps":16,"altAnim":false,"mustHitSection":false,"changeBPM":false,"bpm":175},{"sectionNotes":[[84000,0,0],[84150,0,0],[84600,0,0],[84750,0,0]],"typeOfSection":0,"lengthInSteps":16,"altAnim":false,"mustHitSection":false,"changeBPM":false,"bpm":175},{"sectionNotes":[[85200,2,1125]],"typeOfSection":0,"lengthInSteps":16,"altAnim":false,"mustHitSection":true,"changeBPM":false,"bpm":175},{"sectionNotes":[[86400,1,0],[86550,0,0],[86700,1,0],[86850,0,0],[87000,1,0],[87150,3,0],[87300,1,0],[87450,2,0]],"typeOfSection":0,"lengthInSteps":16,"altAnim":false,"mustHitSection":true,"changeBPM":false,"bpm":175},{"sectionNotes":[[87600,3,525],[88200,3,225],[88500,3,0],[88650,3,0]],"typeOfSection":0,"lengthInSteps":16,"altAnim":false,"mustHitSection":true,"changeBPM":false,"bpm":175},{"sectionNotes":[[88800,1,0],[88950,1,0],[89100,1,0],[89250,1,0],[89400,0,0],[89550,0,0],[89700,3,0],[89850,2,0]],"typeOfSection":0,"lengthInSteps":16,"altAnim":false,"mustHitSection":true,"changeBPM":false,"bpm":175},{"sectionNotes":[[90000,3,1125]],"typeOfSection":0,"lengthInSteps":16,"altAnim":false,"mustHitSection":false,"changeBPM":false,"bpm":175},{"sectionNotes":[[91200,3,1125]],"typeOfSection":0,"lengthInSteps":16,"altAnim":false,"mustHitSection":false,"changeBPM":false,"bpm":175},{"sectionNotes":[[92400,3,0],[92550,3,0],[93000,3,0],[93150,3,0],[93450,3,0]],"typeOfSection":0,"lengthInSteps":16,"altAnim":false,"mustHitSection":false,"changeBPM":false,"bpm":175},{"sectionNotes":[[93600,3,0],[93750,3,0],[94200,3,0],[94350,3,0]],"typeOfSection":0,"lengthInSteps":16,"altAnim":false,"mustHitSection":false,"changeBPM":false,"bpm":175},{"sectionNotes":[[94800,2,1125]],"typeOfSection":0,"lengthInSteps":16,"altAnim":false,"mustHitSection":true,"changeBPM":false,"bpm":175},{"sectionNotes":[[96150,0,0],[96300,1,0],[96450,0,0],[96600,1,0],[96750,3,0],[96900,1,0],[97050,2,0],[96000,1,0]],"typeOfSection":0,"lengthInSteps":16,"altAnim":false,"mustHitSection":true,"changeBPM":false,"bpm":175},{"sectionNotes":[[97200,3,525],[97800,3,225],[98100,3,0],[98250,3,0]],"typeOfSection":0,"lengthInSteps":16,"altAnim":false,"mustHitSection":true,"changeBPM":false,"bpm":175},{"sectionNotes":[[98400,1,0],[98550,1,0],[98700,1,0],[98850,1,0],[99000,0,0],[99150,0,0],[99300,3,0],[99450,2,0]],"typeOfSection":0,"lengthInSteps":16,"altAnim":false,"mustHitSection":true,"changeBPM":false,"bpm":175},{"sectionNotes":[],"typeOfSection":0,"lengthInSteps":16,"altAnim":false,"mustHitSection":false,"changeBPM":false,"bpm":175},{"sectionNotes":[],"typeOfSection":0,"lengthInSteps":16,"altAnim":false,"mustHitSection":false,"changeBPM":false,"bpm":175},{"sectionNotes":[],"typeOfSection":0,"lengthInSteps":16,"altAnim":false,"mustHitSection":false,"changeBPM":false,"bpm":175},{"sectionNotes":[],"typeOfSection":0,"lengthInSteps":16,"altAnim":false,"mustHitSection":false,"changeBPM":false,"bpm":175},{"sectionNotes":[],"typeOfSection":0,"lengthInSteps":16,"altAnim":false,"mustHitSection":false,"changeBPM":false,"bpm":175},{"sectionNotes":[[105600,1,1125],[105600,3,0]],"typeOfSection":0,"lengthInSteps":16,"altAnim":false,"mustHitSection":false,"changeBPM":false,"bpm":175},{"sectionNotes":[[107250,1,0],[107250,3,0],[107400,3,0],[107400,1,0],[107550,1,0],[107550,3,0],[107850,1,0],[107850,3,0],[106800,1,0],[106950,1,0],[106950,3,0],[106800,3,0]],"typeOfSection":0,"lengthInSteps":16,"altAnim":false,"mustHitSection":false,"changeBPM":false,"bpm":175},{"sectionNotes":[[108000,2,1125],[108000,0,0]],"typeOfSection":0,"lengthInSteps":16,"altAnim":false,"mustHitSection":false,"changeBPM":false,"bpm":175},{"sectionNotes":[[109200,2,0],[109350,2,0],[109500,2,0],[109800,2,0],[109950,2,0],[110250,2,0],[109200,0,0],[109350,0,0],[109500,0,0],[109800,0,0],[109950,0,0],[110250,0,0]],"typeOfSection":0,"lengthInSteps":16,"altAnim":false,"mustHitSection":false,"changeBPM":false,"bpm":175},{"sectionNotes":[[110400,0,1125]],"typeOfSection":0,"lengthInSteps":16,"altAnim":false,"mustHitSection":true,"changeBPM":false,"bpm":175},{"sectionNotes":[[111600,0,0],[111750,0,0],[112200,0,0],[112350,0,0],[112500,0,0],[112650,1,0]],"typeOfSection":0,"lengthInSteps":16,"altAnim":false,"mustHitSection":true,"changeBPM":false,"bpm":175},{"sectionNotes":[[112800,2,525],[113400,2,225],[113700,2,0],[113850,2,0]],"typeOfSection":0,"lengthInSteps":16,"altAnim":false,"mustHitSection":true,"changeBPM":false,"bpm":175},{"sectionNotes":[[114000,2,0],[114150,1,0],[114300,2,0],[114450,2,0],[114600,1,0],[114750,2,0],[114900,1,0],[115050,3,0]],"typeOfSection":0,"lengthInSteps":16,"altAnim":false,"mustHitSection":true,"changeBPM":false,"bpm":175},{"sectionNotes":[[115200,0,0],[115350,0,0],[115500,0,0],[115800,0,0],[115950,0,0],[116100,0,0],[116250,0,0],[115200,3,0],[115350,3,0],[115500,3,0],[115800,3,0],[115950,3,0],[116100,3,0],[116250,3,0]],"typeOfSection":0,"lengthInSteps":16,"altAnim":false,"mustHitSection":false,"changeBPM":false,"bpm":175},{"sectionNotes":[[116400,0,1125],[116400,3,1125]],"typeOfSection":0,"lengthInSteps":16,"altAnim":false,"mustHitSection":false,"changeBPM":false,"bpm":175},{"sectionNotes":[[117600,0,0],[117750,0,0],[117900,0,0],[118200,0,0],[118350,0,0],[118500,0,0],[118650,1,0],[118725,2,0]],"typeOfSection":0,"lengthInSteps":16,"altAnim":false,"mustHitSection":true,"changeBPM":false,"bpm":175},{"sectionNotes":[[118800,3,525],[119400,3,225],[119700,3,0],[119850,3,0]],"typeOfSection":0,"lengthInSteps":16,"altAnim":false,"mustHitSection":true,"changeBPM":false,"bpm":175},{"sectionNotes":[[120000,0,0],[120150,0,0],[120300,0,0],[120600,0,0],[120750,0,0],[120900,0,0],[121050,0,0],[120000,3,0],[120150,3,0],[120300,3,0],[120600,3,0],[120750,3,0],[120900,3,0],[121050,3,0]],"typeOfSection":0,"lengthInSteps":16,"altAnim":false,"mustHitSection":false,"changeBPM":false,"bpm":175},{"sectionNotes":[[121200,0,1125],[121200,3,1125]],"typeOfSection":0,"lengthInSteps":16,"altAnim":false,"mustHitSection":false,"changeBPM":false,"bpm":175},{"sectionNotes":[[122400,0,0],[122550,0,0],[122700,0,0],[123000,0,0],[123150,0,0],[123300,0,0],[123450,1,0],[123525,2,0]],"typeOfSection":0,"lengthInSteps":16,"altAnim":false,"mustHitSection":true,"changeBPM":false,"bpm":175},{"sectionNotes":[],"typeOfSection":0,"lengthInSteps":16,"altAnim":false,"mustHitSection":true,"changeBPM":false,"bpm":175},{"sectionNotes":[[124800,3,0],[124950,2,0],[125100,2,0],[125250,3,0],[125400,2,0],[125550,2,0],[125700,2,0]],"typeOfSection":0,"lengthInSteps":16,"altAnim":false,"mustHitSection":false,"changeBPM":false,"bpm":175},{"sectionNotes":[[126000,3,0],[126150,2,0],[126300,2,0],[126450,2,0],[126600,2,0],[126900,2,0],[127050,2,0]],"typeOfSection":0,"lengthInSteps":16,"altAnim":false,"mustHitSection":false,"changeBPM":false,"bpm":175},{"sectionNotes":[[127200,0,0],[127875,0,0],[128100,0,0],[127200,1,0],[127275,2,0],[127275,3,0],[127350,0,0],[127350,1,0],[127500,0,0],[127500,1,0],[127575,2,0],[127575,3,0],[127650,0,0],[127650,1,0],[128050,3,0],[128300,3,0]],"typeOfSection":0,"lengthInSteps":16,"altAnim":false,"mustHitSection":false,"changeBPM":false,"bpm":175},{"sectionNotes":[[128400,3,1125]],"typeOfSection":0,"lengthInSteps":16,"altAnim":false,"mustHitSection":false,"changeBPM":false,"bpm":175},{"sectionNotes":[[129600,2,0],[129750,3,0],[129900,0,0],[129975,1,0],[130200,3,0],[130350,0,0],[130500,1,0],[130650,0,0],[130725,0,0],[130050,2,0]],"typeOfSection":0,"lengthInSteps":16,"altAnim":false,"mustHitSection":true,"changeBPM":false,"bpm":175},{"lengthInSteps":16,"typeOfSection":0,"sectionNotes":[[130800,3,0],[130950,3,0],[131100,0,0],[131364.375,0,0],[131850,2,0],[131700,0,0],[131775,0,0],[131400,2,0],[131550,2,0]],"altAnim":false,"bpm":175,"changeBPM":false,"mustHitSection":true},{"sectionNotes":[[132000,1,0],[132150,3,0],[132300,3,0],[132375,3,0],[132450,0,0],[132600,1,0],[132750,1,0],[132900,1,0],[133050,0,0],[132825,2,0],[132975,2,0]],"typeOfSection":0,"lengthInSteps":16,"altAnim":false,"mustHitSection":true,"changeBPM":false,"bpm":175},{"lengthInSteps":16,"typeOfSection":0,"sectionNotes":[[133200,1,0],[133350,3,0],[133500,1,0],[133650,3,0],[133800,0,0],[133950,1,0],[134100,0,0],[134250,1,0]],"altAnim":false,"bpm":175,"changeBPM":false,"mustHitSection":true},{"lengthInSteps":16,"typeOfSection":0,"sectionNotes":[[134700,0,225],[135000,1,225],[135300,3,75],[135450,2,75]],"altAnim":false,"bpm":175,"changeBPM":false,"mustHitSection":false},{"lengthInSteps":16,"typeOfSection":0,"sectionNotes":[[135600,3,75],[135750,2,375],[136200,0,0],[136350,3,0],[136500,0,0],[136650,3,0]],"altAnim":false,"bpm":175,"changeBPM":false,"mustHitSection":false},{"sectionNotes":[[136800,4,0],[136950,7,0],[137400,2,0],[137550,3,0],[137700,1,0],[137775,0,0],[137850,2,0]],"typeOfSection":0,"lengthInSteps":16,"altAnim":false,"mustHitSection":true,"changeBPM":false,"bpm":175},{"sectionNotes":[[138600,1,0],[138750,2,0],[138825,2,0],[138900,3,0],[139050,3,0],[138000,2,0],[138150,3,0],[138300,1,0],[138375,0,0],[138450,2,0]],"typeOfSection":0,"lengthInSteps":16,"altAnim":false,"mustHitSection":true,"changeBPM":false,"bpm":175},{"sectionNotes":[[139200,6,0],[139425,6,0],[140025,0,75],[140250,1,75]],"typeOfSection":0,"lengthInSteps":16,"altAnim":false,"mustHitSection":false,"changeBPM":false,"bpm":175},{"sectionNotes":[[140400,0,75],[140700,1,75],[140850,3,0],[141000,0,0],[141150,2,0],[141300,3,0],[141450,1,300]],"typeOfSection":0,"lengthInSteps":16,"altAnim":false,"mustHitSection":false,"changeBPM":false,"bpm":175},{"sectionNotes":[[142200,2,0],[142350,2,0],[142500,2,0],[142200,6,0],[142350,6,0],[142500,6,0],[142650,2,0],[142650,6,0]],"typeOfSection":0,"lengthInSteps":16,"altAnim":false,"mustHitSection":true,"changeBPM":false,"bpm":175},{"sectionNotes":[[143400,4,525],[143400,0,525],[142800,2,0],[142800,6,0],[142950,2,0],[142950,6,0],[143100,2,0],[143100,6,0],[143175,1,0],[143175,5,0],[143250,6,0],[143250,2,0]],"typeOfSection":0,"lengthInSteps":16,"altAnim":false,"mustHitSection":false,"changeBPM":false,"bpm":175},{"lengthInSteps":16,"typeOfSection":0,"sectionNotes":[[144000,3,225],[144300,3,0],[144450,1,0],[144600,3,0],[144675,0,0],[144750,1,0],[144900,3,0],[144975,0,0],[144375,0,0],[144000,7,225],[144300,4,0],[144300,5,0],[144450,6,0],[144450,7,0],[144600,4,0],[144600,5,0],[144750,6,0],[144750,7,0],[145050,1,0],[144900,5,225],[144900,4,225]],"altAnim":false,"bpm":175,"changeBPM":false,"mustHitSection":true},{"sectionNotes":[[145200,5,1575]],"typeOfSection":0,"lengthInSteps":16,"altAnim":false,"mustHitSection":false,"changeBPM":false,"bpm":175},{"lengthInSteps":16,"typeOfSection":0,"sectionNotes":[],"altAnim":false,"bpm":175,"changeBPM":false,"mustHitSection":true},{"lengthInSteps":16,"typeOfSection":0,"sectionNotes":[],"altAnim":false,"bpm":200,"changeBPM":false,"mustHitSection":true},{"lengthInSteps":16,"typeOfSection":0,"sectionNotes":[],"altAnim":false,"bpm":200,"changeBPM":false,"mustHitSection":false},{"lengthInSteps":16,"typeOfSection":0,"sectionNotes":[],"altAnim":false,"bpm":200,"changeBPM":false,"mustHitSection":false},{"lengthInSteps":16,"typeOfSection":0,"sectionNotes":[],"altAnim":false,"bpm":200,"changeBPM":false,"mustHitSection":false},{"lengthInSteps":16,"typeOfSection":0,"sectionNotes":[],"altAnim":false,"bpm":200,"changeBPM":false,"mustHitSection":false},{"lengthInSteps":16,"typeOfSection":0,"sectionNotes":[],"altAnim":false,"bpm":200,"changeBPM":false,"mustHitSection":true},{"lengthInSteps":16,"typeOfSection":0,"sectionNotes":[],"altAnim":false,"bpm":200,"changeBPM":false,"mustHitSection":true},{"lengthInSteps":16,"typeOfSection":0,"sectionNotes":[],"altAnim":false,"bpm":200,"changeBPM":false,"mustHitSection":true},{"lengthInSteps":16,"typeOfSection":0,"sectionNotes":[],"altAnim":false,"bpm":200,"changeBPM":false,"mustHitSection":true},{"lengthInSteps":16,"typeOfSection":0,"sectionNotes":[],"altAnim":false,"bpm":200,"changeBPM":false,"mustHitSection":false},{"lengthInSteps":16,"typeOfSection":0,"sectionNotes":[],"altAnim":false,"bpm":200,"changeBPM":false,"mustHitSection":false},{"lengthInSteps":16,"typeOfSection":0,"sectionNotes":[],"altAnim":false,"bpm":200,"changeBPM":false,"mustHitSection":false},{"lengthInSteps":16,"typeOfSection":0,"sectionNotes":[],"altAnim":false,"bpm":200,"changeBPM":false,"mustHitSection":false},{"lengthInSteps":16,"typeOfSection":0,"sectionNotes":[],"altAnim":false,"bpm":200,"changeBPM":false,"mustHitSection":true},{"lengthInSteps":16,"typeOfSection":0,"sectionNotes":[],"altAnim":false,"bpm":200,"changeBPM":false,"mustHitSection":true},{"lengthInSteps":16,"typeOfSection":0,"sectionNotes":[],"altAnim":false,"bpm":200,"changeBPM":false,"mustHitSection":true},{"lengthInSteps":16,"typeOfSection":0,"sectionNotes":[[166800,2,375]],"altAnim":false,"bpm":200,"changeBPM":false,"mustHitSection":true},{"lengthInSteps":16,"typeOfSection":0,"sectionNotes":[],"altAnim":false,"bpm":200,"changeBPM":false,"mustHitSection":true},{"lengthInSteps":16,"typeOfSection":0,"sectionNotes":[[170250,1,600],[169350,2,600]],"altAnim":false,"bpm":200,"changeBPM":false,"mustHitSection":true},{"lengthInSteps":16,"typeOfSection":0,"sectionNotes":[[171075,3,600]],"altAnim":false,"bpm":200,"changeBPM":false,"mustHitSection":true},{"lengthInSteps":16,"typeOfSection":0,"sectionNotes":[[171975,2,600]],"altAnim":false,"bpm":200,"changeBPM":false,"mustHitSection":true},{"lengthInSteps":16,"typeOfSection":0,"sectionNotes":[[172854.545454545,3,600],[173727.272727273,0,225]],"altAnim":false,"bpm":200,"changeBPM":false,"mustHitSection":true},{"lengthInSteps":16,"typeOfSection":0,"sectionNotes":[],"altAnim":false,"bpm":200,"changeBPM":false,"mustHitSection":true},{"lengthInSteps":16,"typeOfSection":0,"sectionNotes":[],"altAnim":false,"bpm":200,"changeBPM":false,"mustHitSection":true},{"lengthInSteps":16,"typeOfSection":0,"sectionNotes":[[176625,0,0],[176775,1,0],[176925,0,0],[177075,1,0],[177225,2,600]],"altAnim":false,"bpm":200,"changeBPM":false,"mustHitSection":true},{"lengthInSteps":16,"typeOfSection":0,"sectionNotes":[[178050,3,600]],"altAnim":false,"bpm":200,"changeBPM":false,"mustHitSection":true},{"lengthInSteps":16,"typeOfSection":0,"sectionNotes":[[179850,1,675],[178950,0,600]],"altAnim":false,"bpm":200,"changeBPM":false,"mustHitSection":true},{"lengthInSteps":16,"typeOfSection":0,"sectionNotes":[[180750,3,225]],"altAnim":false,"bpm":200,"changeBPM":false,"mustHitSection":true},{"lengthInSteps":16,"typeOfSection":0,"sectionNotes":[],"altAnim":false,"bpm":200,"changeBPM":false,"mustHitSection":true},{"lengthInSteps":16,"typeOfSection":0,"sectionNotes":[],"altAnim":false,"bpm":200,"changeBPM":false,"mustHitSection":true},{"lengthInSteps":16,"typeOfSection":0,"sectionNotes":[[183825,0,0],[183975,1,0],[184125,0,0],[184275,3,525],[183675,1,0]],"altAnim":false,"bpm":200,"changeBPM":false,"mustHitSection":true},{"lengthInSteps":16,"typeOfSection":0,"sectionNotes":[[185100,0,600]],"altAnim":false,"bpm":200,"changeBPM":false,"mustHitSection":true},{"lengthInSteps":16,"typeOfSection":0,"sectionNotes":[[186000,2,600],[186825,3,525]],"altAnim":false,"bpm":200,"changeBPM":false,"mustHitSection":true},{"lengthInSteps":16,"typeOfSection":0,"sectionNotes":[[187725,1,150]],"altAnim":false,"bpm":200,"changeBPM":false,"mustHitSection":true},{"lengthInSteps":16,"typeOfSection":0,"sectionNotes":[],"altAnim":false,"bpm":200,"changeBPM":false,"mustHitSection":true},{"lengthInSteps":16,"typeOfSection":0,"sectionNotes":[[190650,3,0]],"altAnim":false,"bpm":200,"changeBPM":false,"mustHitSection":true},{"lengthInSteps":16,"typeOfSection":0,"sectionNotes":[[190800,0,0],[190950,3,0],[191100,0,0],[191250,2,525]],"altAnim":false,"bpm":200,"changeBPM":false,"mustHitSection":true},{"lengthInSteps":16,"typeOfSection":0,"sectionNotes":[[192075,3,525],[192975,0,600]],"altAnim":false,"bpm":200,"changeBPM":false,"mustHitSection":true},{"lengthInSteps":16,"typeOfSection":0,"sectionNotes":[[193875,1,600]],"altAnim":false,"bpm":200,"changeBPM":false,"mustHitSection":true},{"lengthInSteps":16,"typeOfSection":0,"sectionNotes":[[194775,3,225]],"altAnim":false,"bpm":200,"changeBPM":false,"mustHitSection":true},{"lengthInSteps":16,"typeOfSection":0,"sectionNotes":[],"altAnim":false,"bpm":200,"changeBPM":false,"mustHitSection":true},{"lengthInSteps":16,"typeOfSection":0,"sectionNotes":[],"altAnim":false,"bpm":200,"changeBPM":false,"mustHitSection":true},{"lengthInSteps":16,"typeOfSection":0,"sectionNotes":[],"altAnim":false,"bpm":200,"changeBPM":false,"mustHitSection":true},{"lengthInSteps":16,"typeOfSection":0,"sectionNotes":[],"altAnim":false,"bpm":200,"changeBPM":false,"mustHitSection":true},{"lengthInSteps":16,"typeOfSection":0,"sectionNotes":[],"altAnim":false,"bpm":200,"changeBPM":false,"mustHitSection":true},{"lengthInSteps":16,"typeOfSection":0,"sectionNotes":[[202200,1,225],[202500,0,225]],"altAnim":false,"bpm":200,"changeBPM":false,"mustHitSection":true},{"lengthInSteps":16,"typeOfSection":0,"sectionNotes":[[202800,1,225],[203100,3,225],[203400,1,225]],"altAnim":false,"bpm":200,"changeBPM":false,"mustHitSection":true},{"lengthInSteps":16,"typeOfSection":0,"sectionNotes":[[204075,2,225],[204450,1,75],[204600,3,0],[205125,1,450]],"altAnim":false,"bpm":200,"changeBPM":false,"mustHitSection":true},{"lengthInSteps":16,"typeOfSection":0,"sectionNotes":[[206100,2,300],[205612.5,0,225]],"altAnim":false,"bpm":200,"changeBPM":false,"mustHitSection":true},{"lengthInSteps":16,"typeOfSection":0,"sectionNotes":[[206475,0,300],[206850,1,300],[207225,3,450]],"altAnim":false,"bpm":200,"changeBPM":false,"mustHitSection":true},{"lengthInSteps":16,"typeOfSection":0,"sectionNotes":[[207750,0,375],[208275,3,1650]],"altAnim":false,"bpm":200,"changeBPM":false,"mustHitSection":true},{"lengthInSteps":16,"typeOfSection":0,"sectionNotes":[],"altAnim":false,"bpm":200,"changeBPM":false,"mustHitSection":true},{"lengthInSteps":16,"typeOfSection":0,"sectionNotes":[],"altAnim":false,"bpm":200,"changeBPM":false,"mustHitSection":true},{"lengthInSteps":16,"typeOfSection":0,"sectionNotes":[],"altAnim":false,"bpm":200,"changeBPM":false,"mustHitSection":true},{"lengthInSteps":16,"typeOfSection":0,"sectionNotes":[],"altAnim":false,"bpm":200,"changeBPM":false,"mustHitSection":true},{"lengthInSteps":16,"typeOfSection":0,"sectionNotes":[],"altAnim":false,"bpm":200,"changeBPM":false,"mustHitSection":true},{"lengthInSteps":16,"typeOfSection":0,"sectionNotes":[],"altAnim":false,"bpm":200,"changeBPM":false,"mustHitSection":true},{"lengthInSteps":16,"typeOfSection":0,"sectionNotes":[],"altAnim":false,"bpm":200,"changeBPM":false,"mustHitSection":true},{"lengthInSteps":16,"typeOfSection":0,"sectionNotes":[],"altAnim":false,"bpm":200,"changeBPM":false,"mustHitSection":true},{"lengthInSteps":16,"typeOfSection":0,"sectionNotes":[],"altAnim":false,"bpm":200,"changeBPM":false,"mustHitSection":true},{"lengthInSteps":16,"typeOfSection":0,"sectionNotes":[],"altAnim":false,"bpm":200,"changeBPM":false,"mustHitSection":true},{"lengthInSteps":16,"typeOfSection":0,"sectionNotes":[],"altAnim":false,"bpm":200,"changeBPM":false,"mustHitSection":true},{"lengthInSteps":16,"typeOfSection":0,"sectionNotes":[],"altAnim":false,"bpm":200,"changeBPM":false,"mustHitSection":true},{"lengthInSteps":16,"typeOfSection":0,"sectionNotes":[],"altAnim":false,"bpm":200,"changeBPM":false,"mustHitSection":true},{"lengthInSteps":16,"typeOfSection":0,"sectionNotes":[],"altAnim":false,"bpm":200,"changeBPM":false,"mustHitSection":true},{"lengthInSteps":16,"typeOfSection":0,"sectionNotes":[],"altAnim":false,"bpm":200,"changeBPM":false,"mustHitSection":true},{"lengthInSteps":16,"typeOfSection":0,"sectionNotes":[],"altAnim":false,"bpm":200,"changeBPM":false,"mustHitSection":true},{"lengthInSteps":16,"typeOfSection":0,"sectionNotes":[],"altAnim":false,"bpm":200,"changeBPM":false,"mustHitSection":true},{"lengthInSteps":16,"typeOfSection":0,"sectionNotes":[],"altAnim":false,"bpm":200,"changeBPM":false,"mustHitSection":true},{"lengthInSteps":16,"typeOfSection":0,"sectionNotes":[],"altAnim":false,"bpm":200,"changeBPM":false,"mustHitSection":true},{"lengthInSteps":16,"typeOfSection":0,"sectionNotes":[],"altAnim":false,"bpm":200,"changeBPM":false,"mustHitSection":true},{"lengthInSteps":16,"typeOfSection":0,"sectionNotes":[[233925,4,0],[233923,4,0],[233915,4,0],[233911,4,0],[233883,4,0],[233878,4,0],[233872,4,0],[233866,4,0],[233844,4,0],[233806,4,0],[233799,4,0],[233784,4,0],[233767,4,0],[233750,4,0],[233741,4,0],[233737,4,0],[233730,4,0],[233730,4,0],[233713,4,0],[233707,4,0],[233705,4,0],[233698,4,0],[233692,4,0],[233683,4,0],[233673,4,0],[233666,4,0],[233658,4,0],[233645,4,0],[233632,4,0],[233626,4,0],[233602,4,0],[233593,4,0],[233583,4,0],[233563,4,0],[233561,4,0],[233551,4,0],[233548,4,0],[233527,4,0],[233525,4,0],[233521,4,0],[233508,4,0],[233503,4,0],[233497,4,0],[233488,4,0],[233480,4,0],[233478,4,0],[233465,4,0],[233448,4,0],[233407,4,0],[233390,4,0],[233386,4,0],[233341,4,0],[233325,4,0],[233310,4,0],[233295,4,0],[233287,4,0],[233281,4,0],[233270,4,0],[233218,4,0],[233205,4,0],[233188,4,0],[233176,4,0],[233165,4,0],[233154,4,0],[233145,4,0],[233139,4,0],[233130,4,0],[233118,4,0],[233113,4,0],[233083,4,0],[233040,4,0],[233032,4,0],[233019,4,0],[232980,4,0],[232972,4,0],[232961,4,0],[232953,4,0],[232946,4,0],[232920,4,0],[232901,4,0],[232897,4,0],[232895,4,0],[232880,4,0],[232865,4,0],[232861,4,0],[232845,4,0],[232833,4,0],[232822,4,0],[232815,4,0],[232805,4,0],[233925,0,0],[233923,0,0],[233915,0,0],[233911,0,0],[233883,0,0],[233878,0,0],[233872,0,0],[233866,0,0],[233844,0,0],[233806,0,0],[233799,0,0],[233784,0,0],[233767,0,0],[233750,0,0],[233741,0,0],[233737,0,0],[233730,0,0],[233730,0,0],[233713,0,0],[233707,0,0],[233705,0,0],[233698,0,0],[233692,0,0],[233683,0,0],[233673,0,0],[233666,0,0],[233658,0,0],[233645,0,0],[233632,0,0],[233626,0,0],[233602,0,0],[233593,0,0],[233583,0,0],[233563,0,0],[233561,0,0],[233551,0,0],[233548,0,0],[233527,0,0],[233525,0,0],[233521,0,0],[233508,0,0],[233503,0,0],[233497,0,0],[233488,0,0],[233480,0,0],[233478,0,0],[233465,0,0],[233448,0,0],[233407,0,0],[233390,0,0],[233386,0,0],[233341,0,0],[233325,0,0],[233310,0,0],[233295,0,0],[233287,0,0],[233281,0,0],[233270,0,0],[233218,0,0],[233205,0,0],[233188,0,0],[233176,0,0],[233165,0,0],[233154,0,0],[233145,0,0],[233139,0,0],[233130,0,0],[233118,0,0],[233113,0,0],[233083,0,0],[233040,0,0],[233032,0,0],[233019,0,0],[232980,0,0],[232972,0,0],[232961,0,0],[232953,0,0],[232946,0,0],[232920,0,0],[232901,0,0],[232897,0,0],[232895,0,0],[232880,0,0],[232865,0,0],[232861,0,0],[232845,0,0],[232833,0,0],[232822,0,0],[232815,0,0],[232805,0,0],[233925,4,0],[233923,4,0],[233915,4,0],[233911,4,0],[233883,4,0],[233878,4,0],[233872,4,0],[233866,4,0],[233844,4,0],[233806,4,0],[233799,4,0],[233784,4,0],[233767,4,0],[233750,4,0],[233741,4,0],[233737,4,0],[233730,4,0],[233730,4,0],[233713,4,0],[233707,4,0],[233705,4,0],[233698,4,0],[233692,4,0],[233683,4,0],[233673,4,0],[233666,4,0],[233658,4,0],[233645,4,0],[233632,4,0],[233626,4,0],[233602,4,0],[233593,4,0],[233583,4,0],[233563,4,0],[233561,4,0],[233551,4,0],[233548,4,0],[233527,4,0],[233525,4,0],[233521,4,0],[233508,4,0],[233503,4,0],[233497,4,0],[233488,4,0],[233480,4,0],[233478,4,0],[233465,4,0],[233448,4,0],[233407,4,0],[233390,4,0],[233386,4,0],[233341,4,0],[233325,4,0],[233310,4,0],[233295,4,0],[233287,4,0],[233281,4,0],[233270,4,0],[233218,4,0],[233205,4,0],[233188,4,0],[233176,4,0],[233165,4,0],[233154,4,0],[233145,4,0],[233139,4,0],[233130,4,0],[233118,4,0],[233113,4,0],[233083,4,0],[233040,4,0],[233032,4,0],[233019,4,0],[232980,4,0],[232972,4,0],[232961,4,0],[232953,4,0],[232946,4,0],[232920,4,0],[232901,4,0],[232897,4,0],[232895,4,0],[232880,4,0],[232865,4,0],[232861,4,0],[232845,4,0],[232833,4,0],[232822,4,0],[232815,4,0],[232805,4,0],[233921,5,0],[233904,5,0],[233896,5,0],[233885,5,0],[233878,5,0],[233863,5,0],[233855,5,0],[233848,5,0],[233838,5,0],[233823,5,0],[233810,5,0],[233803,5,0],[233791,5,0],[233782,5,0],[233773,5,0],[233765,5,0],[233760,5,0],[233748,5,0],[233739,5,0],[233728,5,0],[233715,5,0],[233707,5,0],[233700,5,0],[233690,5,0],[233683,5,0],[233671,5,0],[233664,5,0],[233658,5,0],[233643,5,0],[233621,5,0],[233611,5,0],[233604,5,0],[233593,5,0],[233581,5,0],[233565,5,0],[233550,5,0],[233527,5,0],[233520,5,0],[233508,5,0],[233482,5,0],[233465,5,0],[233448,5,0],[233435,5,0],[233426,5,0],[233416,5,0],[233413,5,0],[233401,5,0],[233396,5,0],[233383,5,0],[233371,5,0],[233356,5,0],[233343,5,0],[233332,5,0],[233315,5,0],[233306,5,0],[233300,5,0],[233295,5,0],[233283,5,0],[233276,5,0],[233266,5,0],[233255,5,0],[233248,5,0],[233235,5,0],[233227,5,0],[233212,5,0],[233197,5,0],[233190,5,0],[233175,5,0],[233146,5,0],[233128,5,0],[233115,5,0],[233094,5,0],[233079,5,0],[233070,5,0],[233062,5,0],[233043,5,0],[233040,5,0],[233036,5,0],[233023,5,0],[233019,5,0],[233011,5,0],[233000,5,0],[232987,5,0],[232981,5,0],[232974,5,0],[232965,5,0],[232951,5,0],[232948,5,0],[232944,5,0],[232938,5,0],[232925,5,0],[232912,5,0],[232899,5,0],[232893,5,0],[232886,5,0],[232871,5,0],[232852,5,0],[232835,5,0],[232818,5,0],[232813,5,0],[232811,5,0],[232801,5,0],[233926,6,0],[233921,6,0],[233915,6,0],[233913,6,0],[233906,6,0],[233898,6,0],[233893,6,0],[233887,6,0],[233878,6,0],[233872,6,0],[233868,6,0],[233855,6,0],[233850,6,0],[233844,6,0],[233838,6,0],[233829,6,0],[233820,6,0],[233806,6,0],[233801,6,0],[233795,6,0],[233784,6,0],[233780,6,0],[233771,6,0],[233752,6,0],[233746,6,0],[233741,6,0],[233733,6,0],[233722,6,0],[233707,6,0],[233700,6,0],[233690,6,0],[233685,6,0],[233679,6,0],[233671,6,0],[233664,6,0],[233660,6,0],[233651,6,0],[233640,6,0],[233634,6,0],[233621,6,0],[233610,6,0],[233602,6,0],[233596,6,0],[233587,6,0],[233578,6,0],[233568,6,0],[233559,6,0],[233550,6,0],[233542,6,0],[233529,6,0],[233501,6,0],[233488,6,0],[233475,6,0],[233461,6,0],[233450,6,0],[233437,6,0],[233424,6,0],[233409,6,0],[233401,6,0],[233398,6,0],[233377,6,0],[233356,6,0],[233351,6,0],[233341,6,0],[233330,6,0],[233321,6,0],[233313,6,0],[233300,6,0],[233283,6,0],[233270,6,0],[233257,6,0],[233251,6,0],[233248,6,0],[233242,6,0],[233223,6,0],[233208,6,0],[233201,6,0],[233182,6,0],[233152,6,0],[233145,6,0],[233137,6,0],[233131,6,0],[233124,6,0],[233116,6,0],[233105,6,0],[233098,6,0],[233094,6,0],[233083,6,0],[233062,6,0],[233060,6,0],[233053,6,0],[233028,6,0],[233008,6,0],[233006,6,0],[232993,6,0],[232991,6,0],[232989,6,0],[232974,6,0],[232972,6,0],[232965,6,0],[232959,6,0],[232940,6,0],[232921,6,0],[232897,6,0],[232884,6,0],[232867,6,0],[232854,6,0],[232843,6,0],[232835,6,0],[232831,6,0],[232820,6,0],[232811,6,0],[233921,7,0],[233910,7,0],[233904,7,0],[233898,7,0],[233887,7,0],[233859,7,0],[233851,7,0],[233846,7,0],[233838,7,0],[233833,7,0],[233825,7,0],[233820,7,0],[233812,7,0],[233805,7,0],[233801,7,0],[233791,7,0],[233784,7,0],[233776,7,0],[233775,7,0],[233773,7,0],[233767,7,0],[233748,7,0],[233733,7,0],[233722,7,0],[233713,7,0],[233707,7,0],[233698,7,0],[233694,7,0],[233686,7,0],[233675,7,0],[233664,7,0],[233655,7,0],[233649,7,0],[233641,7,0],[233634,7,0],[233604,7,0],[233585,7,0],[233574,7,0],[233557,7,0],[233551,7,0],[233540,7,0],[233529,7,0],[233493,7,0],[233469,7,0],[233452,7,0],[233435,7,0],[233418,7,0],[233405,7,0],[233381,7,0],[233373,7,0],[233360,7,0],[233345,7,0],[233330,7,0],[233323,7,0],[233311,7,0],[233298,7,0],[233270,7,0],[233257,7,0],[233248,7,0],[233233,7,0],[233223,7,0],[233212,7,0],[233197,7,0],[233188,7,0],[233173,7,0],[233161,7,0],[233156,7,0],[233148,7,0],[233139,7,0],[233126,7,0],[233113,7,0],[233107,7,0],[233096,7,0],[233088,7,0],[233083,7,0],[233070,7,0],[233053,7,0],[233040,7,0],[233028,7,0],[233017,7,0],[233006,7,0],[232995,7,0],[232989,7,0],[232980,7,0],[232970,7,0],[232961,7,0],[232942,7,0],[232927,7,0],[232912,7,0],[232901,7,0],[232886,7,0],[232876,7,0],[232863,7,0],[232848,7,0],[232824,7,0],[232818,7,0],[232811,7,0],[232801,7,0],[233925,0,0],[233923.125,0,0],[233915.625,0,0],[233911.875,0,0],[233883.75,0,0],[233878.125,0,0],[233872.5,0,0],[233866.875,0,0],[233844.375,0,0],[233806.875,0,0],[233799.375,0,0],[233784.375,0,0],[233767.5,0,0],[233750.625,0,0],[233741.25,0,0],[233737.5,0,0],[233730,0,0],[233730,0,0],[233713.125,0,0],[233707.5,0,0],[233705.625,0,0],[233698.125,0,0],[233692.5,0,0],[233683.125,0,0],[233673.75,0,0],[233666.25,0,0],[233658.75,0,0],[233645.625,0,0],[233632.5,0,0],[233626.875,0,0],[233602.5,0,0],[233593.125,0,0],[233583.75,0,0],[233563.125,0,0],[233561.25,0,0],[233551.875,0,0],[233548.125,0,0],[233527.5,0,0],[233525.625,0,0],[233521.875,0,0],[233508.75,0,0],[233503.125,0,0],[233497.5,0,0],[233488.125,0,0],[233480.625,0,0],[233478.75,0,0],[233465.625,0,0],[233448.75,0,0],[233407.5,0,0],[233390.625,0,0],[233386.875,0,0],[233341.875,0,0],[233325,0,0],[233310,0,0],[233295,0,0],[233287.5,0,0],[233281.875,0,0],[233270.625,0,0],[233218.125,0,0],[233205,0,0],[233188.125,0,0],[233176.875,0,0],[233165.625,0,0],[233154.375,0,0],[233145,0,0],[233139.375,0,0],[233130,0,0],[233118.75,0,0],[233113.125,0,0],[233083.125,0,0],[233040,0,0],[233032.5,0,0],[233019.375,0,0],[232980,0,0],[232972.5,0,0],[232961.25,0,0],[232953.75,0,0],[232946.25,0,0],[232920,0,0],[232901.25,0,0],[232897.5,0,0],[232895.625,0,0],[232880.625,0,0],[232865.625,0,0],[232861.875,0,0],[232845,0,0],[232833.75,0,0],[232822.5,0,0],[232815,0,0],[232805.625,0,0],[233925,4,0],[233923,4,0],[233915,4,0],[233911,4,0],[233883,4,0],[233878,4,0],[233872,4,0],[233866,4,0],[233844,4,0],[233806,4,0],[233799,4,0],[233784,4,0],[233767,4,0],[233750,4,0],[233741,4,0],[233737,4,0],[233730,4,0],[233730,4,0],[233713,4,0],[233707,4,0],[233705,4,0],[233698,4,0],[233692,4,0],[233683,4,0],[233673,4,0],[233666,4,0],[233658,4,0],[233645,4,0],[233632,4,0],[233626,4,0],[233602,4,0],[233593,4,0],[233583,4,0],[233563,4,0],[233561,4,0],[233551,4,0],[233548,4,0],[233527,4,0],[233525,4,0],[233521,4,0],[233508,4,0],[233503,4,0],[233497,4,0],[233488,4,0],[233480,4,0],[233478,4,0],[233465,4,0],[233448,4,0],[233407,4,0],[233390,4,0],[233386,4,0],[233341,4,0],[233325,4,0],[233310,4,0],[233295,4,0],[233287,4,0],[233281,4,0],[233270,4,0],[233218,4,0],[233205,4,0],[233188,4,0],[233176,4,0],[233165,4,0],[233154,4,0],[233145,4,0],[233139,4,0],[233130,4,0],[233118,4,0],[233113,4,0],[233083,4,0],[233040,4,0],[233032,4,0],[233019,4,0],[232980,4,0],[232972,4,0],[232961,4,0],[232953,4,0],[232946,4,0],[232920,4,0],[232901,4,0],[232897,4,0],[232895,4,0],[232880,4,0],[232865,4,0],[232861,4,0],[232845,4,0],[232833,4,0],[232822,4,0],[232815,4,0],[232805,4,0],[233925,0,0],[233923.125,0,0],[233915.625,0,0],[233911.875,0,0],[233883.75,0,0],[233878.125,0,0],[233872.5,0,0],[233866.875,0,0],[233844.375,0,0],[233806.875,0,0],[233799.375,0,0],[233784.375,0,0],[233767.5,0,0],[233750.625,0,0],[233741.25,0,0],[233737.5,0,0],[233730,0,0],[233730,0,0],[233713.125,0,0],[233707.5,0,0],[233705.625,0,0],[233698.125,0,0],[233692.5,0,0],[233683.125,0,0],[233673.75,0,0],[233666.25,0,0],[233658.75,0,0],[233645.625,0,0],[233632.5,0,0],[233626.875,0,0],[233602.5,0,0],[233593.125,0,0],[233583.75,0,0],[233563.125,0,0],[233561.25,0,0],[233551.875,0,0],[233548.125,0,0],[233527.5,0,0],[233525.625,0,0],[233521.875,0,0],[233508.75,0,0],[233503.125,0,0],[233497.5,0,0],[233488.125,0,0],[233480.625,0,0],[233478.75,0,0],[233465.625,0,0],[233448.75,0,0],[233407.5,0,0],[233390.625,0,0],[233386.875,0,0],[233341.875,0,0],[233325,0,0],[233310,0,0],[233295,0,0],[233287.5,0,0],[233281.875,0,0],[233270.625,0,0],[233218.125,0,0],[233205,0,0],[233188.125,0,0],[233176.875,0,0],[233165.625,0,0],[233154.375,0,0],[233145,0,0],[233139.375,0,0],[233130,0,0],[233118.75,0,0],[233113.125,0,0],[233083.125,0,0],[233040,0,0],[233032.5,0,0],[233019.375,0,0],[232980,0,0],[232972.5,0,0],[232961.25,0,0],[232953.75,0,0],[232946.25,0,0],[232920,0,0],[232901.25,0,0],[232897.5,0,0],[232895.625,0,0],[232880.625,0,0],[232865.625,0,0],[232861.875,0,0],[232845,0,0],[232833.75,0,0],[232822.5,0,0],[232815,0,0],[232805.625,0,0],[233921.25,1,0],[233904.375,1,0],[233896.875,1,0],[233885.625,1,0],[233878.125,1,0],[233863.125,1,0],[233855.625,1,0],[233848.125,1,0],[233838.75,1,0],[233823.75,1,0],[233810.625,1,0],[233803.125,1,0],[233791.875,1,0],[233782.5,1,0],[233773.125,1,0],[233765.625,1,0],[233760,1,0],[233748.75,1,0],[233739.375,1,0],[233728.125,1,0],[233715,1,0],[233707.5,1,0],[233700,1,0],[233690.625,1,0],[233683.125,1,0],[233671.875,1,0],[233664.375,1,0],[233658.75,1,0],[233643.75,1,0],[233621.25,1,0],[233611.875,1,0],[233604.375,1,0],[233593.125,1,0],[233581.875,1,0],[233565,1,0],[233550,1,0],[233527.5,1,0],[233520,1,0],[233508.75,1,0],[233482.5,1,0],[233465.625,1,0],[233448.75,1,0],[233435.625,1,0],[233426.25,1,0],[233416.875,1,0],[233413.125,1,0],[233401.875,1,0],[233396.25,1,0],[233383.125,1,0],[233371.875,1,0],[233356.875,1,0],[233343.75,1,0],[233332.5,1,0],[233315.625,1,0],[233306.25,1,0],[233300.625,1,0],[233295,1,0],[233283.75,1,0],[233276.25,1,0],[233266.875,1,0],[233255.625,1,0],[233248.125,1,0],[233235,1,0],[233227.5,1,0],[233212.5,1,0],[233197.5,1,0],[233190,1,0],[233175,1,0],[233146.875,1,0],[233128.125,1,0],[233115,1,0],[233094.375,1,0],[233079.375,1,0],[233070,1,0],[233062.5,1,0],[233043.75,1,0],[233040,1,0],[233036.25,1,0],[233023.125,1,0],[233019.375,1,0],[233011.875,1,0],[233000.625,1,0],[232987.5,1,0],[232981.875,1,0],[232974.375,1,0],[232965,1,0],[232951.875,1,0],[232948.125,1,0],[232944.375,1,0],[232938.75,1,0],[232925.625,1,0],[232912.5,1,0],[232899.375,1,0],[232893.75,1,0],[232886.25,1,0],[232871.25,1,0],[232852.5,1,0],[232835.625,1,0],[232818.75,1,0],[232813.125,1,0],[232811.25,1,0],[232801.875,1,0],[233926.875,2,0],[233921.25,2,0],[233915.625,2,0],[233913.75,2,0],[233906.25,2,0],[233898.75,2,0],[233893.125,2,0],[233887.5,2,0],[233878.125,2,0],[233872.5,2,0],[233868.75,2,0],[233855.625,2,0],[233850,2,0],[233844.375,2,0],[233838.75,2,0],[233829.375,2,0],[233820,2,0],[233806.875,2,0],[233801.25,2,0],[233795.625,2,0],[233784.375,2,0],[233780.625,2,0],[233771.25,2,0],[233752.5,2,0],[233746.875,2,0],[233741.25,2,0],[233733.75,2,0],[233722.5,2,0],[233707.5,2,0],[233700,2,0],[233690.625,2,0],[233685,2,0],[233679.375,2,0],[233671.875,2,0],[233664.375,2,0],[233660.625,2,0],[233651.25,2,0],[233640,2,0],[233634.375,2,0],[233621.25,2,0],[233610,2,0],[233602.5,2,0],[233596.875,2,0],[233587.5,2,0],[233578.125,2,0],[233568.75,2,0],[233559.375,2,0],[233550,2,0],[233542.5,2,0],[233529.375,2,0],[233501.25,2,0],[233488.125,2,0],[233475,2,0],[233461.875,2,0],[233450.625,2,0],[233437.5,2,0],[233424.375,2,0],[233409.375,2,0],[233401.875,2,0],[233398.125,2,0],[233377.5,2,0],[233356.875,2,0],[233351.25,2,0],[233341.875,2,0],[233330.625,2,0],[233321.25,2,0],[233313.75,2,0],[233300.625,2,0],[233283.75,2,0],[233270.625,2,0],[233257.5,2,0],[233251.875,2,0],[233248.125,2,0],[233242.5,2,0],[233223.75,2,0],[233208.75,2,0],[233201.25,2,0],[233182.5,2,0],[233152.5,2,0],[233145,2,0],[233137.5,2,0],[233131.875,2,0],[233124.375,2,0],[233116.875,2,0],[233105.625,2,0],[233098.125,2,0],[233094.375,2,0],[233083.125,2,0],[233062.5,2,0],[233060.625,2,0],[233053.125,2,0],[233028.75,2,0],[233008.125,2,0],[233006.25,2,0],[232993.125,2,0],[232991.25,2,0],[232989.375,2,0],[232974.375,2,0],[232972.5,2,0],[232965,2,0],[232959.375,2,0],[232940.625,2,0],[232921.875,2,0],[232897.5,2,0],[232884.375,2,0],[232867.5,2,0],[232854.375,2,0],[232843.125,2,0],[232835.625,2,0],[232831.875,2,0],[232820.625,2,0],[232811.25,2,0],[233921.25,3,0],[233910,3,0],[233904.375,3,0],[233898.75,3,0],[233887.5,3,0],[233859.375,3,0],[233851.875,3,0],[233846.25,3,0],[233838.75,3,0],[233833.125,3,0],[233825.625,3,0],[233820,3,0],[233812.5,3,0],[233805,3,0],[233801.25,3,0],[233791.875,3,0],[233784.375,3,0],[233776.875,3,0],[233775,3,0],[233773.125,3,0],[233767.5,3,0],[233748.75,3,0],[233733.75,3,0],[233722.5,3,0],[233713.125,3,0],[233707.5,3,0],[233698.125,3,0],[233694.375,3,0],[233686.875,3,0],[233675.625,3,0],[233664.375,3,0],[233655,3,0],[233649.375,3,0],[233641.875,3,0],[233634.375,3,0],[233604.375,3,0],[233585.625,3,0],[233574.375,3,0],[233557.5,3,0],[233551.875,3,0],[233540.625,3,0],[233529.375,3,0],[233493.75,3,0],[233469.375,3,0],[233452.5,3,0],[233435.625,3,0],[233418.75,3,0],[233405.625,3,0],[233381.25,3,0],[233373.75,3,0],[233360.625,3,0],[233345.625,3,0],[233330.625,3,0],[233323.125,3,0],[233311.875,3,0],[233298.75,3,0],[233270.625,3,0],[233257.5,3,0],[233248.125,3,0],[233233.125,3,0],[233223.75,3,0],[233212.5,3,0],[233197.5,3,0],[233188.125,3,0],[233173.125,3,0],[233161.875,3,0],[233156.25,3,0],[233148.75,3,0],[233139.375,3,0],[233126.25,3,0],[233113.125,3,0],[233107.5,3,0],[233096.25,3,0],[233088.75,3,0],[233083.125,3,0],[233070,3,0],[233053.125,3,0],[233040,3,0],[233028.75,3,0],[233017.5,3,0],[233006.25,3,0],[232995,3,0],[232989.375,3,0],[232980,3,0],[232970.625,3,0],[232961.25,3,0],[232942.5,3,0],[232927.5,3,0],[232912.5,3,0],[232901.25,3,0],[232886.25,3,0],[232876.875,3,0],[232863.75,3,0],[232848.75,3,0],[232824.375,3,0],[232818.75,3,0],[232811.25,3,0],[232801.875,3,0]],"altAnim":false,"bpm":200,"changeBPM":false,"mustHitSection":true},{"lengthInSteps":16,"typeOfSection":0,"sectionNotes":[[235125,4,0],[235123,4,0],[235115,4,0],[235111,4,0],[235083,4,0],[235078,4,0],[235072,4,0],[235066,4,0],[235044,4,0],[235006,4,0],[234999,4,0],[234984,4,0],[234967,4,0],[234950,4,0],[234941,4,0],[234937,4,0],[234930,4,0],[234930,4,0],[234913,4,0],[234907,4,0],[234905,4,0],[234898,4,0],[234892,4,0],[234883,4,0],[234873,4,0],[234866,4,0],[234858,4,0],[234845,4,0],[234832,4,0],[234826,4,0],[234802,4,0],[234793,4,0],[234783,4,0],[234763,4,0],[234761,4,0],[234751,4,0],[234748,4,0],[234727,4,0],[234725,4,0],[234721,4,0],[234708,4,0],[234703,4,0],[234697,4,0],[234688,4,0],[234680,4,0],[234678,4,0],[234665,4,0],[234648,4,0],[234607,4,0],[234590,4,0],[234586,4,0],[234541,4,0],[234525,4,0],[234510,4,0],[234495,4,0],[234487,4,0],[234481,4,0],[234470,4,0],[234418,4,0],[234405,4,0],[234388,4,0],[234376,4,0],[234365,4,0],[234354,4,0],[234345,4,0],[234339,4,0],[234330,4,0],[234318,4,0],[234313,4,0],[234283,4,0],[234240,4,0],[234232,4,0],[234219,4,0],[234180,4,0],[234172,4,0],[234161,4,0],[234153,4,0],[234146,4,0],[234120,4,0],[234101,4,0],[234097,4,0],[234095,4,0],[234080,4,0],[234065,4,0],[234061,4,0],[234045,4,0],[234033,4,0],[234022,4,0],[234015,4,0],[234005,4,0],[235125,0,0],[235123,0,0],[235115,0,0],[235111,0,0],[235083,0,0],[235078,0,0],[235072,0,0],[235066,0,0],[235044,0,0],[235006,0,0],[234999,0,0],[234984,0,0],[234967,0,0],[234950,0,0],[234941,0,0],[234937,0,0],[234930,0,0],[234930,0,0],[234913,0,0],[234907,0,0],[234905,0,0],[234898,0,0],[234892,0,0],[234883,0,0],[234873,0,0],[234866,0,0],[234858,0,0],[234845,0,0],[234832,0,0],[234826,0,0],[234802,0,0],[234793,0,0],[234783,0,0],[234763,0,0],[234761,0,0],[234751,0,0],[234748,0,0],[234727,0,0],[234725,0,0],[234721,0,0],[234708,0,0],[234703,0,0],[234697,0,0],[234688,0,0],[234680,0,0],[234678,0,0],[234665,0,0],[234648,0,0],[234607,0,0],[234590,0,0],[234586,0,0],[234541,0,0],[234525,0,0],[234510,0,0],[234495,0,0],[234487,0,0],[234481,0,0],[234470,0,0],[234418,0,0],[234405,0,0],[234388,0,0],[234376,0,0],[234365,0,0],[234354,0,0],[234345,0,0],[234339,0,0],[234330,0,0],[234318,0,0],[234313,0,0],[234283,0,0],[234240,0,0],[234232,0,0],[234219,0,0],[234180,0,0],[234172,0,0],[234161,0,0],[234153,0,0],[234146,0,0],[234120,0,0],[234101,0,0],[234097,0,0],[234095,0,0],[234080,0,0],[234065,0,0],[234061,0,0],[234045,0,0],[234033,0,0],[234022,0,0],[234015,0,0],[234005,0,0],[235125,4,0],[235123,4,0],[235115,4,0],[235111,4,0],[235083,4,0],[235078,4,0],[235072,4,0],[235066,4,0],[235044,4,0],[235006,4,0],[234999,4,0],[234984,4,0],[234967,4,0],[234950,4,0],[234941,4,0],[234937,4,0],[234930,4,0],[234930,4,0],[234913,4,0],[234907,4,0],[234905,4,0],[234898,4,0],[234892,4,0],[234883,4,0],[234873,4,0],[234866,4,0],[234858,4,0],[234845,4,0],[234832,4,0],[234826,4,0],[234802,4,0],[234793,4,0],[234783,4,0],[234763,4,0],[234761,4,0],[234751,4,0],[234748,4,0],[234727,4,0],[234725,4,0],[234721,4,0],[234708,4,0],[234703,4,0],[234697,4,0],[234688,4,0],[234680,4,0],[234678,4,0],[234665,4,0],[234648,4,0],[234607,4,0],[234590,4,0],[234586,4,0],[234541,4,0],[234525,4,0],[234510,4,0],[234495,4,0],[234487,4,0],[234481,4,0],[234470,4,0],[234418,4,0],[234405,4,0],[234388,4,0],[234376,4,0],[234365,4,0],[234354,4,0],[234345,4,0],[234339,4,0],[234330,4,0],[234318,4,0],[234313,4,0],[234283,4,0],[234240,4,0],[234232,4,0],[234219,4,0],[234180,4,0],[234172,4,0],[234161,4,0],[234153,4,0],[234146,4,0],[234120,4,0],[234101,4,0],[234097,4,0],[234095,4,0],[234080,4,0],[234065,4,0],[234061,4,0],[234045,4,0],[234033,4,0],[234022,4,0],[234015,4,0],[234005,4,0],[235121,5,0],[235104,5,0],[235096,5,0],[235085,5,0],[235078,5,0],[235063,5,0],[235055,5,0],[235048,5,0],[235038,5,0],[235023,5,0],[235010,5,0],[235003,5,0],[234991,5,0],[234982,5,0],[234973,5,0],[234965,5,0],[234960,5,0],[234948,5,0],[234939,5,0],[234928,5,0],[234915,5,0],[234907,5,0],[234900,5,0],[234890,5,0],[234883,5,0],[234871,5,0],[234864,5,0],[234858,5,0],[234843,5,0],[234821,5,0],[234811,5,0],[234804,5,0],[234793,5,0],[234781,5,0],[234765,5,0],[234750,5,0],[234727,5,0],[234720,5,0],[234708,5,0],[234682,5,0],[234665,5,0],[234648,5,0],[234635,5,0],[234626,5,0],[234616,5,0],[234613,5,0],[234601,5,0],[234596,5,0],[234583,5,0],[234571,5,0],[234556,5,0],[234543,5,0],[234532,5,0],[234515,5,0],[234506,5,0],[234500,5,0],[234495,5,0],[234483,5,0],[234476,5,0],[234466,5,0],[234455,5,0],[234448,5,0],[234435,5,0],[234427,5,0],[234412,5,0],[234397,5,0],[234390,5,0],[234375,5,0],[234346,5,0],[234328,5,0],[234315,5,0],[234294,5,0],[234279,5,0],[234270,5,0],[234262,5,0],[234243,5,0],[234240,5,0],[234236,5,0],[234223,5,0],[234219,5,0],[234211,5,0],[234200,5,0],[234187,5,0],[234181,5,0],[234174,5,0],[234165,5,0],[234151,5,0],[234148,5,0],[234144,5,0],[234138,5,0],[234125,5,0],[234112,5,0],[234099,5,0],[234093,5,0],[234086,5,0],[234071,5,0],[234052,5,0],[234035,5,0],[234018,5,0],[234013,5,0],[234011,5,0],[234001,5,0],[235126,6,0],[235121,6,0],[235115,6,0],[235113,6,0],[235106,6,0],[235098,6,0],[235093,6,0],[235087,6,0],[235078,6,0],[235072,6,0],[235068,6,0],[235055,6,0],[235050,6,0],[235044,6,0],[235038,6,0],[235029,6,0],[235020,6,0],[235006,6,0],[235001,6,0],[234995,6,0],[234984,6,0],[234980,6,0],[234971,6,0],[234952,6,0],[234946,6,0],[234941,6,0],[234933,6,0],[234922,6,0],[234907,6,0],[234900,6,0],[234890,6,0],[234885,6,0],[234879,6,0],[234871,6,0],[234864,6,0],[234860,6,0],[234851,6,0],[234840,6,0],[234834,6,0],[234821,6,0],[234810,6,0],[234802,6,0],[234796,6,0],[234787,6,0],[234778,6,0],[234768,6,0],[234759,6,0],[234750,6,0],[234742,6,0],[234729,6,0],[234701,6,0],[234688,6,0],[234675,6,0],[234661,6,0],[234650,6,0],[234637,6,0],[234624,6,0],[234609,6,0],[234601,6,0],[234598,6,0],[234577,6,0],[234556,6,0],[234551,6,0],[234541,6,0],[234530,6,0],[234521,6,0],[234513,6,0],[234500,6,0],[234483,6,0],[234470,6,0],[234457,6,0],[234451,6,0],[234448,6,0],[234442,6,0],[234423,6,0],[234408,6,0],[234401,6,0],[234382,6,0],[234352,6,0],[234345,6,0],[234337,6,0],[234331,6,0],[234324,6,0],[234316,6,0],[234305,6,0],[234298,6,0],[234294,6,0],[234283,6,0],[234262,6,0],[234260,6,0],[234253,6,0],[234228,6,0],[234208,6,0],[234206,6,0],[234193,6,0],[234191,6,0],[234189,6,0],[234174,6,0],[234172,6,0],[234165,6,0],[234159,6,0],[234140,6,0],[234121,6,0],[234097,6,0],[234084,6,0],[234067,6,0],[234054,6,0],[234043,6,0],[234035,6,0],[234031,6,0],[234020,6,0],[234011,6,0],[235121,7,0],[235110,7,0],[235104,7,0],[235098,7,0],[235087,7,0],[235059,7,0],[235051,7,0],[235046,7,0],[235038,7,0],[235033,7,0],[235025,7,0],[235020,7,0],[235012,7,0],[235005,7,0],[235001,7,0],[234991,7,0],[234984,7,0],[234976,7,0],[234975,7,0],[234973,7,0],[234967,7,0],[234948,7,0],[234933,7,0],[234922,7,0],[234913,7,0],[234907,7,0],[234898,7,0],[234894,7,0],[234886,7,0],[234875,7,0],[234864,7,0],[234855,7,0],[234849,7,0],[234841,7,0],[234834,7,0],[234804,7,0],[234785,7,0],[234774,7,0],[234757,7,0],[234751,7,0],[234740,7,0],[234729,7,0],[234693,7,0],[234669,7,0],[234652,7,0],[234635,7,0],[234618,7,0],[234605,7,0],[234581,7,0],[234573,7,0],[234560,7,0],[234545,7,0],[234530,7,0],[234523,7,0],[234511,7,0],[234498,7,0],[234470,7,0],[234457,7,0],[234448,7,0],[234433,7,0],[234423,7,0],[234412,7,0],[234397,7,0],[234388,7,0],[234373,7,0],[234361,7,0],[234356,7,0],[234348,7,0],[234339,7,0],[234326,7,0],[234313,7,0],[234307,7,0],[234296,7,0],[234288,7,0],[234283,7,0],[234270,7,0],[234253,7,0],[234240,7,0],[234228,7,0],[234217,7,0],[234206,7,0],[234195,7,0],[234189,7,0],[234180,7,0],[234170,7,0],[234161,7,0],[234142,7,0],[234127,7,0],[234112,7,0],[234101,7,0],[234086,7,0],[234076,7,0],[234063,7,0],[234048,7,0],[234024,7,0],[234018,7,0],[234011,7,0],[234001,7,0],[235125,0,0],[235123.125,0,0],[235115.625,0,0],[235111.875,0,0],[235083.75,0,0],[235078.125,0,0],[235072.5,0,0],[235066.875,0,0],[235044.375,0,0],[235006.875,0,0],[234999.375,0,0],[234984.375,0,0],[234967.5,0,0],[234950.625,0,0],[234941.25,0,0],[234937.5,0,0],[234930,0,0],[234930,0,0],[234913.125,0,0],[234907.5,0,0],[234905.625,0,0],[234898.125,0,0],[234892.5,0,0],[234883.125,0,0],[234873.75,0,0],[234866.25,0,0],[234858.75,0,0],[234845.625,0,0],[234832.5,0,0],[234826.875,0,0],[234802.5,0,0],[234793.125,0,0],[234783.75,0,0],[234763.125,0,0],[234761.25,0,0],[234751.875,0,0],[234748.125,0,0],[234727.5,0,0],[234725.625,0,0],[234721.875,0,0],[234708.75,0,0],[234703.125,0,0],[234697.5,0,0],[234688.125,0,0],[234680.625,0,0],[234678.75,0,0],[234665.625,0,0],[234648.75,0,0],[234607.5,0,0],[234590.625,0,0],[234586.875,0,0],[234541.875,0,0],[234525,0,0],[234510,0,0],[234495,0,0],[234487.5,0,0],[234481.875,0,0],[234470.625,0,0],[234418.125,0,0],[234405,0,0],[234388.125,0,0],[234376.875,0,0],[234365.625,0,0],[234354.375,0,0],[234345,0,0],[234339.375,0,0],[234330,0,0],[234318.75,0,0],[234313.125,0,0],[234283.125,0,0],[234240,0,0],[234232.5,0,0],[234219.375,0,0],[234180,0,0],[234172.5,0,0],[234161.25,0,0],[234153.75,0,0],[234146.25,0,0],[234120,0,0],[234101.25,0,0],[234097.5,0,0],[234095.625,0,0],[234080.625,0,0],[234065.625,0,0],[234061.875,0,0],[234045,0,0],[234033.75,0,0],[234022.5,0,0],[234015,0,0],[234005.625,0,0],[235125,4,0],[235123,4,0],[235115,4,0],[235111,4,0],[235083,4,0],[235078,4,0],[235072,4,0],[235066,4,0],[235044,4,0],[235006,4,0],[234999,4,0],[234984,4,0],[234967,4,0],[234950,4,0],[234941,4,0],[234937,4,0],[234930,4,0],[234930,4,0],[234913,4,0],[234907,4,0],[234905,4,0],[234898,4,0],[234892,4,0],[234883,4,0],[234873,4,0],[234866,4,0],[234858,4,0],[234845,4,0],[234832,4,0],[234826,4,0],[234802,4,0],[234793,4,0],[234783,4,0],[234763,4,0],[234761,4,0],[234751,4,0],[234748,4,0],[234727,4,0],[234725,4,0],[234721,4,0],[234708,4,0],[234703,4,0],[234697,4,0],[234688,4,0],[234680,4,0],[234678,4,0],[234665,4,0],[234648,4,0],[234607,4,0],[234590,4,0],[234586,4,0],[234541,4,0],[234525,4,0],[234510,4,0],[234495,4,0],[234487,4,0],[234481,4,0],[234470,4,0],[234418,4,0],[234405,4,0],[234388,4,0],[234376,4,0],[234365,4,0],[234354,4,0],[234345,4,0],[234339,4,0],[234330,4,0],[234318,4,0],[234313,4,0],[234283,4,0],[234240,4,0],[234232,4,0],[234219,4,0],[234180,4,0],[234172,4,0],[234161,4,0],[234153,4,0],[234146,4,0],[234120,4,0],[234101,4,0],[234097,4,0],[234095,4,0],[234080,4,0],[234065,4,0],[234061,4,0],[234045,4,0],[234033,4,0],[234022,4,0],[234015,4,0],[234005,4,0],[235125,0,0],[235123.125,0,0],[235115.625,0,0],[235111.875,0,0],[235083.75,0,0],[235078.125,0,0],[235072.5,0,0],[235066.875,0,0],[235044.375,0,0],[235006.875,0,0],[234999.375,0,0],[234984.375,0,0],[234967.5,0,0],[234950.625,0,0],[234941.25,0,0],[234937.5,0,0],[234930,0,0],[234930,0,0],[234913.125,0,0],[234907.5,0,0],[234905.625,0,0],[234898.125,0,0],[234892.5,0,0],[234883.125,0,0],[234873.75,0,0],[234866.25,0,0],[234858.75,0,0],[234845.625,0,0],[234832.5,0,0],[234826.875,0,0],[234802.5,0,0],[234793.125,0,0],[234783.75,0,0],[234763.125,0,0],[234761.25,0,0],[234751.875,0,0],[234748.125,0,0],[234727.5,0,0],[234725.625,0,0],[234721.875,0,0],[234708.75,0,0],[234703.125,0,0],[234697.5,0,0],[234688.125,0,0],[234680.625,0,0],[234678.75,0,0],[234665.625,0,0],[234648.75,0,0],[234607.5,0,0],[234590.625,0,0],[234586.875,0,0],[234541.875,0,0],[234525,0,0],[234510,0,0],[234495,0,0],[234487.5,0,0],[234481.875,0,0],[234470.625,0,0],[234418.125,0,0],[234405,0,0],[234388.125,0,0],[234376.875,0,0],[234365.625,0,0],[234354.375,0,0],[234345,0,0],[234339.375,0,0],[234330,0,0],[234318.75,0,0],[234313.125,0,0],[234283.125,0,0],[234240,0,0],[234232.5,0,0],[234219.375,0,0],[234180,0,0],[234172.5,0,0],[234161.25,0,0],[234153.75,0,0],[234146.25,0,0],[234120,0,0],[234101.25,0,0],[234097.5,0,0],[234095.625,0,0],[234080.625,0,0],[234065.625,0,0],[234061.875,0,0],[234045,0,0],[234033.75,0,0],[234022.5,0,0],[234015,0,0],[234005.625,0,0],[235121.25,1,0],[235104.375,1,0],[235096.875,1,0],[235085.625,1,0],[235078.125,1,0],[235063.125,1,0],[235055.625,1,0],[235048.125,1,0],[235038.75,1,0],[235023.75,1,0],[235010.625,1,0],[235003.125,1,0],[234991.875,1,0],[234982.5,1,0],[234973.125,1,0],[234965.625,1,0],[234960,1,0],[234948.75,1,0],[234939.375,1,0],[234928.125,1,0],[234915,1,0],[234907.5,1,0],[234900,1,0],[234890.625,1,0],[234883.125,1,0],[234871.875,1,0],[234864.375,1,0],[234858.75,1,0],[234843.75,1,0],[234821.25,1,0],[234811.875,1,0],[234804.375,1,0],[234793.125,1,0],[234781.875,1,0],[234765,1,0],[234750,1,0],[234727.5,1,0],[234720,1,0],[234708.75,1,0],[234682.5,1,0],[234665.625,1,0],[234648.75,1,0],[234635.625,1,0],[234626.25,1,0],[234616.875,1,0],[234613.125,1,0],[234601.875,1,0],[234596.25,1,0],[234583.125,1,0],[234571.875,1,0],[234556.875,1,0],[234543.75,1,0],[234532.5,1,0],[234515.625,1,0],[234506.25,1,0],[234500.625,1,0],[234495,1,0],[234483.75,1,0],[234476.25,1,0],[234466.875,1,0],[234455.625,1,0],[234448.125,1,0],[234435,1,0],[234427.5,1,0],[234412.5,1,0],[234397.5,1,0],[234390,1,0],[234375,1,0],[234346.875,1,0],[234328.125,1,0],[234315,1,0],[234294.375,1,0],[234279.375,1,0],[234270,1,0],[234262.5,1,0],[234243.75,1,0],[234240,1,0],[234236.25,1,0],[234223.125,1,0],[234219.375,1,0],[234211.875,1,0],[234200.625,1,0],[234187.5,1,0],[234181.875,1,0],[234174.375,1,0],[234165,1,0],[234151.875,1,0],[234148.125,1,0],[234144.375,1,0],[234138.75,1,0],[234125.625,1,0],[234112.5,1,0],[234099.375,1,0],[234093.75,1,0],[234086.25,1,0],[234071.25,1,0],[234052.5,1,0],[234035.625,1,0],[234018.75,1,0],[234013.125,1,0],[234011.25,1,0],[234001.875,1,0],[235126.875,2,0],[235121.25,2,0],[235115.625,2,0],[235113.75,2,0],[235106.25,2,0],[235098.75,2,0],[235093.125,2,0],[235087.5,2,0],[235078.125,2,0],[235072.5,2,0],[235068.75,2,0],[235055.625,2,0],[235050,2,0],[235044.375,2,0],[235038.75,2,0],[235029.375,2,0],[235020,2,0],[235006.875,2,0],[235001.25,2,0],[234995.625,2,0],[234984.375,2,0],[234980.625,2,0],[234971.25,2,0],[234952.5,2,0],[234946.875,2,0],[234941.25,2,0],[234933.75,2,0],[234922.5,2,0],[234907.5,2,0],[234900,2,0],[234890.625,2,0],[234885,2,0],[234879.375,2,0],[234871.875,2,0],[234864.375,2,0],[234860.625,2,0],[234851.25,2,0],[234840,2,0],[234834.375,2,0],[234821.25,2,0],[234810,2,0],[234802.5,2,0],[234796.875,2,0],[234787.5,2,0],[234778.125,2,0],[234768.75,2,0],[234759.375,2,0],[234750,2,0],[234742.5,2,0],[234729.375,2,0],[234701.25,2,0],[234688.125,2,0],[234675,2,0],[234661.875,2,0],[234650.625,2,0],[234637.5,2,0],[234624.375,2,0],[234609.375,2,0],[234601.875,2,0],[234598.125,2,0],[234577.5,2,0],[234556.875,2,0],[234551.25,2,0],[234541.875,2,0],[234530.625,2,0],[234521.25,2,0],[234513.75,2,0],[234500.625,2,0],[234483.75,2,0],[234470.625,2,0],[234457.5,2,0],[234451.875,2,0],[234448.125,2,0],[234442.5,2,0],[234423.75,2,0],[234408.75,2,0],[234401.25,2,0],[234382.5,2,0],[234352.5,2,0],[234345,2,0],[234337.5,2,0],[234331.875,2,0],[234324.375,2,0],[234316.875,2,0],[234305.625,2,0],[234298.125,2,0],[234294.375,2,0],[234283.125,2,0],[234262.5,2,0],[234260.625,2,0],[234253.125,2,0],[234228.75,2,0],[234208.125,2,0],[234206.25,2,0],[234193.125,2,0],[234191.25,2,0],[234189.375,2,0],[234174.375,2,0],[234172.5,2,0],[234165,2,0],[234159.375,2,0],[234140.625,2,0],[234121.875,2,0],[234097.5,2,0],[234084.375,2,0],[234067.5,2,0],[234054.375,2,0],[234043.125,2,0],[234035.625,2,0],[234031.875,2,0],[234020.625,2,0],[234011.25,2,0],[235121.25,3,0],[235110,3,0],[235104.375,3,0],[235098.75,3,0],[235087.5,3,0],[235059.375,3,0],[235051.875,3,0],[235046.25,3,0],[235038.75,3,0],[235033.125,3,0],[235025.625,3,0],[235020,3,0],[235012.5,3,0],[235005,3,0],[235001.25,3,0],[234991.875,3,0],[234984.375,3,0],[234976.875,3,0],[234975,3,0],[234973.125,3,0],[234967.5,3,0],[234948.75,3,0],[234933.75,3,0],[234922.5,3,0],[234913.125,3,0],[234907.5,3,0],[234898.125,3,0],[234894.375,3,0],[234886.875,3,0],[234875.625,3,0],[234864.375,3,0],[234855,3,0],[234849.375,3,0],[234841.875,3,0],[234834.375,3,0],[234804.375,3,0],[234785.625,3,0],[234774.375,3,0],[234757.5,3,0],[234751.875,3,0],[234740.625,3,0],[234729.375,3,0],[234693.75,3,0],[234669.375,3,0],[234652.5,3,0],[234635.625,3,0],[234618.75,3,0],[234605.625,3,0],[234581.25,3,0],[234573.75,3,0],[234560.625,3,0],[234545.625,3,0],[234530.625,3,0],[234523.125,3,0],[234511.875,3,0],[234498.75,3,0],[234470.625,3,0],[234457.5,3,0],[234448.125,3,0],[234433.125,3,0],[234423.75,3,0],[234412.5,3,0],[234397.5,3,0],[234388.125,3,0],[234373.125,3,0],[234361.875,3,0],[234356.25,3,0],[234348.75,3,0],[234339.375,3,0],[234326.25,3,0],[234313.125,3,0],[234307.5,3,0],[234296.25,3,0],[234288.75,3,0],[234283.125,3,0],[234270,3,0],[234253.125,3,0],[234240,3,0],[234228.75,3,0],[234217.5,3,0],[234206.25,3,0],[234195,3,0],[234189.375,3,0],[234180,3,0],[234170.625,3,0],[234161.25,3,0],[234142.5,3,0],[234127.5,3,0],[234112.5,3,0],[234101.25,3,0],[234086.25,3,0],[234076.875,3,0],[234063.75,3,0],[234048.75,3,0],[234024.375,3,0],[234018.75,3,0],[234011.25,3,0],[234001.875,3,0]],"altAnim":false,"bpm":200,"changeBPM":false,"mustHitSection":true},{"lengthInSteps":16,"typeOfSection":0,"sectionNotes":[],"altAnim":false,"bpm":200,"changeBPM":false,"mustHitSection":true},{"lengthInSteps":16,"typeOfSection":0,"sectionNotes":[],"altAnim":false,"bpm":200,"changeBPM":false,"mustHitSection":true},{"lengthInSteps":16,"typeOfSection":0,"sectionNotes":[],"altAnim":false,"bpm":200,"changeBPM":false,"mustHitSection":true},{"sectionNotes":[],"typeOfSection":0,"lengthInSteps":16,"altAnim":false,"mustHitSection":true,"changeBPM":false,"bpm":200},{"sectionNotes":[],"typeOfSection":0,"lengthInSteps":16,"altAnim":false,"mustHitSection":true,"changeBPM":false,"bpm":200},{"sectionNotes":[],"typeOfSection":0,"lengthInSteps":16,"altAnim":false,"mustHitSection":true,"changeBPM":false,"bpm":200},{"sectionNotes":[],"typeOfSection":0,"lengthInSteps":16,"altAnim":false,"mustHitSection":true,"changeBPM":false,"bpm":200},{"sectionNotes":[],"typeOfSection":0,"lengthInSteps":16,"altAnim":false,"mustHitSection":true,"changeBPM":false,"bpm":200},{"lengthInSteps":16,"typeOfSection":0,"sectionNotes":[],"altAnim":false,"bpm":200,"changeBPM":false,"mustHitSection":true},{"lengthInSteps":16,"typeOfSection":0,"sectionNotes":[],"altAnim":false,"bpm":200,"changeBPM":false,"mustHitSection":true},{"sectionNotes":[],"typeOfSection":0,"lengthInSteps":16,"altAnim":false,"mustHitSection":true,"changeBPM":false,"bpm":200},{"lengthInSteps":16,"typeOfSection":0,"sectionNotes":[],"altAnim":false,"bpm":200,"changeBPM":false,"mustHitSection":true},{"sectionNotes":[],"typeOfSection":0,"lengthInSteps":16,"altAnim":false,"mustHitSection":true,"changeBPM":false,"bpm":200},{"lengthInSteps":16,"altAnim":false,"typeOfSection":0,"sectionNotes":[],"bpm":200,"changeBPM":false,"mustHitSection":true}],"player2":"omori","song":"Guilty","sections":0,"needsVoices":true,"stage":"whitespace","validScore":true,"speed":2.7,"bpm":200}}